pygtc/VERSION.txt
pygtc/__init__.py
pygtc/pygtc.py
pygtc/tests/__init__.py
pygtc/tests/test_plotGTC.py
pygtc/tests/baseline/bare.png
pygtc/tests/baseline/chainLabels_noTex.png
pygtc/tests/baseline/chainLabels_withTex.png
pygtc/tests/baseline/colorsOrder.png
pygtc/tests/baseline/do1dPlots.png
pygtc/tests/baseline/doOnly1dPlot.png
pygtc/tests/baseline/figureSize.png
pygtc/tests/baseline/filledPlots.png
pygtc/tests/baseline/img.png
pygtc/tests/baseline/labelRotation.png
pygtc/tests/baseline/mathTextFontSet.png
pygtc/tests/baseline/nBins.png
pygtc/tests/baseline/nContourLevels.png
pygtc/tests/baseline/pandas.png
pygtc/tests/baseline/panelSpacing.png
pygtc/tests/baseline/paramNames_noTex.png
pygtc/tests/baseline/paramNames_withTex.png
pygtc/tests/baseline/plotDensity.png
pygtc/tests/baseline/priors.png
pygtc/tests/baseline/sigmaContourLevels.png
pygtc/tests/baseline/smoothingKernel.png
pygtc/tests/baseline/tickShifts.png
pygtc/tests/baseline/truthLabels_noTex.png
pygtc/tests/baseline/truthLabels_withTex.png
pygtc/tests/baseline/truthLineStyles.png
pygtc/tests/baseline/truthLineStyles_withLegend.png
pyGTC-0.5.0.dist-info/LICENSE.txt
pyGTC-0.5.0.dist-info/METADATA
pyGTC-0.5.0.dist-info/WHEEL
pyGTC-0.5.0.dist-info/top_level.txt
pyGTC-0.5.0.dist-info/RECORD
