Metadata-Version: 2.1
Name: pyGTC
Version: 0.5.0
Summary: Make an awesome giant triangle confusogram (gtc)!
Home-page: http://github.com/sebastianbocquet/pygtc
Author: Sebastian Bocquet and Faustin Carter
Author-email: sebastian.bocquet@gmail.com
License: MIT
Classifier: Development Status :: 4 - Beta
Classifier: Intended Audience :: Science/Research
Classifier: License :: OSI Approved :: MIT License
Classifier: Programming Language :: Python
Classifier: Topic :: Scientific/Engineering :: Visualization
License-File: LICENSE.txt
Requires-Dist: packaging
Requires-Dist: numpy >=1.7.1
Requires-Dist: matplotlib >=2.2
